{
  "_nota": "Datos LXVI Legislatura 2024-2027. Verificar y actualizar en: diputados.gob.mx y senado.gob.mx",
  "_actualizado": "Marzo 2026",
  "comisiones": [
    {
      "id": "ma-diputados",
      "nombre": "Medio Ambiente y Recursos Naturales",
      "camara": "Cámara de Diputados",
      "url": "https://medioambiente.diputados.gob.mx/",
      "ultima_reunion": "2025-03-12",
      "proxima_reunion": "2025-04-09",
      "integrantes": [
        {"n": "Arturo Hernández Tapia", "cargo": "Presidente", "partido": "Morena"},
        {"n": "Itzel Rentería Medina", "cargo": "Secretaria", "partido": "Morena"},
        {"n": "Eduardo Espinoza Pérez", "cargo": "Secretario", "partido": "PT"},
        {"n": "Ana Elizabeth Ayala Leyva", "cargo": "Vocal", "partido": "Morena"},
        {"n": "Ricardo Astudillo Suárez", "cargo": "Vocal", "partido": "PAN"},
        {"n": "Noemí Berenice Luna Ayala", "cargo": "Vocal", "partido": "Morena"},
        {"n": "Sandra Simey Olvera Bautista", "cargo": "Vocal", "partido": "Morena"}
      ]
    },
    {
      "id": "energia-diputados",
      "nombre": "Energía",
      "camara": "Cámara de Diputados",
      "url": "https://energia.diputados.gob.mx/",
      "ultima_reunion": "2025-03-18",
      "proxima_reunion": "2025-04-15",
      "integrantes": [
        {"n": "Marco Antonio Mendoza Bustamante", "cargo": "Presidente", "partido": "Morena"},
        {"n": "Sofía Carvajal Isunza", "cargo": "Secretaria", "partido": "Morena"},
        {"n": "Humberto Pedrero Moreno", "cargo": "Secretario", "partido": "PVEM"},
        {"n": "Elsa Méndez Martínez", "cargo": "Vocal", "partido": "Morena"},
        {"n": "Luis Ángel Espinosa Cházaro", "cargo": "Vocal", "partido": "PRD"},
        {"n": "Rodrigo Fuentes Ávila", "cargo": "Vocal", "partido": "PRI"},
        {"n": "Ana Laura Bernal Camarena", "cargo": "Vocal", "partido": "PT"}
      ]
    },
    {
      "id": "ma-senado",
      "nombre": "Medio Ambiente, Recursos Naturales y Cambio Climático",
      "camara": "Senado de la República",
      "url": "https://www.senado.gob.mx/comisiones/medio_ambiente/",
      "ultima_reunion": "2025-03-05",
      "proxima_reunion": "2025-04-02",
      "integrantes": [
        {"n": "Ana Lilia Rivera Rivera", "cargo": "Presidenta", "partido": "Morena"},
        {"n": "Higinio del Toro Pérez", "cargo": "Secretario", "partido": "Morena"},
        {"n": "Silvia Guadalupe Garza Galván", "cargo": "Secretaria", "partido": "PAN"},
        {"n": "Martha Cecilia Márquez Alvarado", "cargo": "Vocal", "partido": "Morena"},
        {"n": "Cristóbal Arias Solís", "cargo": "Vocal", "partido": "Morena"},
        {"n": "Cora Cecilia Pinedo Alonso", "cargo": "Vocal", "partido": "Morena"},
        {"n": "Manuel Añorve Baños", "cargo": "Vocal", "partido": "PRI"}
      ]
    },
    {
      "id": "energia-senado",
      "nombre": "Energía",
      "camara": "Senado de la República",
      "url": "https://www.senado.gob.mx/comisiones/energia/",
      "ultima_reunion": "2025-03-10",
      "proxima_reunion": "2025-04-07",
      "integrantes": [
        {"n": "Adolfo Romero Lainas", "cargo": "Presidente", "partido": "Morena"},
        {"n": "Verónica Camino Farjat", "cargo": "Secretaria", "partido": "Morena"},
        {"n": "Ernesto Ruffo Appel", "cargo": "Secretario", "partido": "PAN"},
        {"n": "Ángel García Yáñez", "cargo": "Vocal", "partido": "Morena"},
        {"n": "Claudia Edith Anaya Mota", "cargo": "Vocal", "partido": "Morena"},
        {"n": "Juan Manuel Fócil Pérez", "cargo": "Vocal", "partido": "Morena"},
        {"n": "Damián Zepeda Vidales", "cargo": "Vocal", "partido": "PAN"}
      ]
    }
  ]
}